langfun/__init__.py
langfun/core/__init__.py
langfun/core/component.py
langfun/core/component_test.py
langfun/core/concurrent.py
langfun/core/concurrent_test.py
langfun/core/console.py
langfun/core/console_test.py
langfun/core/langfunc.py
langfun/core/langfunc_test.py
langfun/core/language_model.py
langfun/core/language_model_test.py
langfun/core/logging.py
langfun/core/logging_test.py
langfun/core/memory.py
langfun/core/message.py
langfun/core/message_test.py
langfun/core/modality.py
langfun/core/modality_test.py
langfun/core/natural_language.py
langfun/core/natural_language_test.py
langfun/core/repr_utils.py
langfun/core/repr_utils_test.py
langfun/core/sampling.py
langfun/core/sampling_test.py
langfun/core/subscription.py
langfun/core/subscription_test.py
langfun/core/template.py
langfun/core/template_test.py
langfun/core/text_formatting.py
langfun/core/text_formatting_test.py
langfun/core/coding/__init__.py
langfun/core/coding/python/__init__.py
langfun/core/coding/python/correction.py
langfun/core/coding/python/correction_test.py
langfun/core/coding/python/errors.py
langfun/core/coding/python/errors_test.py
langfun/core/coding/python/execution.py
langfun/core/coding/python/execution_test.py
langfun/core/coding/python/generation.py
langfun/core/coding/python/generation_test.py
langfun/core/coding/python/parsing.py
langfun/core/coding/python/parsing_test.py
langfun/core/coding/python/permissions.py
langfun/core/coding/python/permissions_test.py
langfun/core/eval/__init__.py
langfun/core/eval/base.py
langfun/core/eval/base_test.py
langfun/core/eval/matching.py
langfun/core/eval/matching_test.py
langfun/core/eval/patching.py
langfun/core/eval/patching_test.py
langfun/core/eval/scoring.py
langfun/core/eval/scoring_test.py
langfun/core/llms/__init__.py
langfun/core/llms/anthropic.py
langfun/core/llms/anthropic_test.py
langfun/core/llms/fake.py
langfun/core/llms/fake_test.py
langfun/core/llms/google_genai.py
langfun/core/llms/google_genai_test.py
langfun-0.1.1.dist-info/LICENSE
langfun-0.1.1.dist-info/METADATA
langfun-0.1.1.dist-info/WHEEL
langfun-0.1.1.dist-info/top_level.txt
langfun-0.1.1.dist-info/RECORD
