Metadata-Version: 2.1
Name: langfun
Version: 0.1.1
Summary: Langfun: Language as Functions.
Home-page: https://github.com/google/langfun
Author: Langfun Authors
Author-email: langfun-authors@google.com
License: Apache License 2.0
Keywords: llm generative-ai machine-learning
Classifier: Development Status :: 3 - Alpha
Classifier: Intended Audience :: Developers
Classifier: Intended Audience :: Education
Classifier: Intended Audience :: Science/Research
Classifier: License :: OSI Approved :: Apache Software License
Classifier: Programming Language :: Python :: 3
Classifier: Programming Language :: Python :: 3.10
Classifier: Programming Language :: Python :: 3.11
Classifier: Topic :: Scientific/Engineering :: Artificial Intelligence
Classifier: Topic :: Scientific/Engineering :: Human Machine Interfaces
Classifier: Topic :: Software Development :: Libraries :: Python Modules
Classifier: Topic :: Software Development :: Libraries
License-File: LICENSE
Requires-Dist: google-cloud-aiplatform >=1.5.0
Requires-Dist: google-generativeai >=0.3.2
Requires-Dist: jinja2 >=3.1.2
Requires-Dist: openai ==0.27.2
Requires-Dist: openpyxl >=3.1.0
Requires-Dist: pandas >=2.0.3
Requires-Dist: pyglove >=0.4.5.dev20240423
Requires-Dist: python-docx >=0.8.11
Requires-Dist: python-magic >=0.4.27
Requires-Dist: requests >=2.31.0
Requires-Dist: termcolor ==1.1.0
Requires-Dist: tqdm >=4.64.1
Requires-Dist: pillow >=10.0.0
